README.rst
oauth2_proxy_cookie.py
setup.py
oauth2_proxy_cookie.egg-info/PKG-INFO
oauth2_proxy_cookie.egg-info/SOURCES.txt
oauth2_proxy_cookie.egg-info/dependency_links.txt
oauth2_proxy_cookie.egg-info/requires.txt
oauth2_proxy_cookie.egg-info/top_level.txt