Metadata-Version: 1.1
Name: oauth2-proxy-cookie
Version: 0.1.0
Summary: bitly/oauth2-proxy compatible library to decode and validate authenticated cookie.
Home-page: https://github.com/isra17/oauth2-proxy-cookie
Author: isra17
Author-email: isra017@gmail.com
License: LGPLv3+
Keywords: oauth2-proxy authentication
Platform: UNKNOWN
Classifier: Development Status :: 3 - Alpha
Classifier: Intended Audience :: Developers
Classifier: Topic :: Internet :: WWW/HTTP :: HTTP Servers
Classifier: License :: OSI Approved :: GNU Lesser General Public License v3 or later (LGPLv3+)
Classifier: Programming Language :: Python :: 2
Classifier: Programming Language :: Python :: 3
